{
	"totalBalance": 152035,
	"totalIncome": 1256,
	"totalExpense": 458,
    	"currency": "₹",
	"top3Categories": [
		{
			"Name": "Electronics",
			"Percent": 26,
			"Icon": "electronics",
			"Color": "#F9C80E"
		},
		{
			"Name": "Food & Drink",
			"Percent": 19,
			"Icon": "food",
			"Color": "#F86624"
		},
		{
			"Name": "Home",
			"Percent": 43,
			"Icon": "home",
			"Color": "#EA3546"
		},
		{
			"Name": "Others",
			"Percent": 12,
			"Icon": "others",
			"Color": "#43BCCD"
		}
	]
}
